odoo/addons/fiscal_epos_print_meal_voucher/README.rst
odoo/addons/fiscal_epos_print_meal_voucher/__init__.py
odoo/addons/fiscal_epos_print_meal_voucher/__manifest__.py
odoo/addons/fiscal_epos_print_meal_voucher/i18n/fiscal_epos_print_meal_voucher.pot
odoo/addons/fiscal_epos_print_meal_voucher/i18n/it.po
odoo/addons/fiscal_epos_print_meal_voucher/models/__init__.py
odoo/addons/fiscal_epos_print_meal_voucher/models/account_bank_statement.py
odoo/addons/fiscal_epos_print_meal_voucher/models/account_journal.py
odoo/addons/fiscal_epos_print_meal_voucher/models/point_of_sale.py
odoo/addons/fiscal_epos_print_meal_voucher/models/pos_order.py
odoo/addons/fiscal_epos_print_meal_voucher/readme/CONFIGURE.rst
odoo/addons/fiscal_epos_print_meal_voucher/readme/CONTRIBUTORS.rst
odoo/addons/fiscal_epos_print_meal_voucher/readme/DESCRIPTION.rst
odoo/addons/fiscal_epos_print_meal_voucher/static/description/icon.png
odoo/addons/fiscal_epos_print_meal_voucher/static/description/index.html
odoo/addons/fiscal_epos_print_meal_voucher/static/src/js/models.js
odoo/addons/fiscal_epos_print_meal_voucher/static/src/js/screens.js
odoo/addons/fiscal_epos_print_meal_voucher/static/src/xml/pos.xml
odoo/addons/fiscal_epos_print_meal_voucher/views/account_views.xml
odoo/addons/fiscal_epos_print_meal_voucher/views/assets.xml
odoo/addons/fiscal_epos_print_meal_voucher/views/pos_config_views.xml
odoo12_addon_fiscal_epos_print_meal_voucher-12.0.1.1.0.dist-info/METADATA
odoo12_addon_fiscal_epos_print_meal_voucher-12.0.1.1.0.dist-info/WHEEL
odoo12_addon_fiscal_epos_print_meal_voucher-12.0.1.1.0.dist-info/top_level.txt
odoo12_addon_fiscal_epos_print_meal_voucher-12.0.1.1.0.dist-info/RECORD
